LICENSE
README.rst
setup.cfg
setup.py
docs/api.rst
docs/auth.rst
docs/changelog.rst
docs/conf.py
docs/crud.rst
docs/doctests.rst
docs/extend.rst
docs/index.rst
docs/installation.rst
docs/quickstart.rst
src/senaite/__init__.py
src/senaite.jsonapi.egg-info/PKG-INFO
src/senaite.jsonapi.egg-info/SOURCES.txt
src/senaite.jsonapi.egg-info/dependency_links.txt
src/senaite.jsonapi.egg-info/entry_points.txt
src/senaite.jsonapi.egg-info/namespace_packages.txt
src/senaite.jsonapi.egg-info/not-zip-safe
src/senaite.jsonapi.egg-info/requires.txt
src/senaite.jsonapi.egg-info/top_level.txt
src/senaite/jsonapi/__init__.py
src/senaite/jsonapi/api.py
src/senaite/jsonapi/batch.py
src/senaite/jsonapi/catalog.py
src/senaite/jsonapi/config.py
src/senaite/jsonapi/configure.zcml
src/senaite/jsonapi/datamanagers.py
src/senaite/jsonapi/dataproviders.py
src/senaite/jsonapi/exceptions.py
src/senaite/jsonapi/fieldmanagers.py
src/senaite/jsonapi/interfaces.py
src/senaite/jsonapi/request.py
src/senaite/jsonapi/underscore.py
src/senaite/jsonapi/v1/__init__.py
src/senaite/jsonapi/v1/configure.zcml
src/senaite/jsonapi/v1/routes/__init__.py
src/senaite/jsonapi/v1/routes/catalogs.py
src/senaite/jsonapi/v1/routes/content.py
src/senaite/jsonapi/v1/routes/registry.py
src/senaite/jsonapi/v1/routes/settings.py
src/senaite/jsonapi/v1/routes/users.py
src/senaite/jsonapi/v1/routes/version.py