Metadata-Version: 2.1
Name: senaite.jsonapi
Version: 1.2.3
Summary: SENAITE JSON API
Home-page: https://github.com/senaite/senaite.jsonapi
Author: RIDING BYTES & NARALABS
Author-email: senaite@senaite.com
License: GPLv2
Platform: UNKNOWN
Classifier: Framework :: Plone
Classifier: Framework :: Zope2
Classifier: Programming Language :: Python
Classifier: Development Status :: 5 - Production/Stable
Classifier: License :: OSI Approved :: GNU General Public License v2 (GPLv2)
Provides-Extra: test
